setup.py
src/django_processedimagefield.egg-info/PKG-INFO
src/django_processedimagefield.egg-info/SOURCES.txt
src/django_processedimagefield.egg-info/dependency_links.txt
src/django_processedimagefield.egg-info/requires.txt
src/django_processedimagefield.egg-info/top_level.txt
src/processedimagefield/__init__.py
src/processedimagefield/fields.py
src/processedimagefield/transforms.py