Metadata-Version: 1.0
Name: django-processedimagefield
Version: 0.1
Summary: Post-processing for Django ImageFields.
Home-page: https://github.com/nathforge/django-processedimagefield
Author: Nathan Reynolds
Author-email: email@nreynolds.co.uk
License: UNKNOWN
Platform: UNKNOWN
